badi_ticket/__init__.py
badi_ticket/admin.py
badi_ticket/api.py
badi_ticket/apps.py
badi_ticket/models.py
badi_ticket/routers.py
badi_ticket/serializers.py
badi_ticket/urls.py
badi_ticket/views.py
badi_ticket/migrations/__init__.py
badi_ticket/templates/__init__.py
badi_user/__init__.py
badi_user/admin.py
badi_user/apps.py
badi_user/filter.py
badi_user/models.py
badi_user/api/api.py
badi_user/api/routers.py
badi_user/api/serializers.py
badi_user/migrations/__init__.py
badi_user/templatetags/__init__.py
badi_user/templatetags/appfilter.py
badi_user/ui/forms.py
badi_user/ui/log_views.py
badi_user/ui/member_views.py
badi_user/ui/notification_views.py
badi_user/ui/roles_views.py
badi_user/ui/urls.py
badi_user/ui/views.py
badi_wallet/__init__.py
badi_wallet/action.py
badi_wallet/admin.py
badi_wallet/apps.py
badi_wallet/models.py
badi_wallet/api/routers.py
badi_wallet/api/serializers.py
badi_wallet/api/view_sets.py
badi_wallet/migrations/__init__.py
badi_wallet/templates/__init__.py
badi_wallet/ui/urls.py
badi_wallet/ui/views.py
badi_users-0.1.8.dist-info/METADATA
badi_users-0.1.8.dist-info/WHEEL
badi_users-0.1.8.dist-info/licenses/LICENSE
badi_users-0.1.8.dist-info/RECORD
