Metadata-Version: 2.1
Name: badi_users
Version: 0.1.8
Summary: Python Django Users
Project-URL: Homepage, https://github.com/BadiDesign/badi_utils
Project-URL: Bug Tracker, https://github.com/BadiDesign/badi_utils/issues
Author-email: Mohammad Shekari Badi <Ad.BadiDesign@gmail.com>
License: Copyright (c) 2022 The Python Packaging Authority
License-File: LICENSE
Classifier: License :: OSI Approved :: MIT License
Classifier: Operating System :: OS Independent
Classifier: Programming Language :: Python :: 3
Requires-Python: >=3.7
